LICENSE
README.md
setup.py
boat_fib_py/__init__.py
boat_fib_py.egg-info/PKG-INFO
boat_fib_py.egg-info/SOURCES.txt
boat_fib_py.egg-info/dependency_links.txt
boat_fib_py.egg-info/entry_points.txt
boat_fib_py.egg-info/top_level.txt
boat_fib_py/cmd/__init__.py
boat_fib_py/cmd/fib_numb.py
boat_fib_py/fib_calcs/__init__.py
boat_fib_py/fib_calcs/fib_number.py
boat_fib_py/fib_calcs/fib_numbers.py
tests/boat_fib_py/__init__.py
tests/boat_fib_py/fib_calcs/__init__.py
tests/boat_fib_py/fib_calcs/test_fib_number.py
tests/boat_fib_py/fib_calcs/test_fib_numbers.py